ffgo/__init__.py
ffgo/common_transl.py
ffgo/config.py
ffgo/constants.py
ffgo/exceptions.py
ffgo/fgcmdbuilder.py
ffgo/logging.py
ffgo/main.py
ffgo/misc.py
ffgo/stats_manager.py
ffgo/data/config/config_de
ffgo/data/config/config_en
ffgo/data/config/config_es
ffgo/data/config/config_fr
ffgo/data/config/config_it
ffgo/data/config/config_ja
ffgo/data/config/config_pl
ffgo/data/config/presets
ffgo/data/help/help_de
ffgo/data/help/help_en
ffgo/data/help/help_es
ffgo/data/help/help_fr
ffgo/data/help/help_it
ffgo/data/help/help_ja
ffgo/data/help/help_pl
ffgo/data/locale/de/LC_MESSAGES/FFGo.mo
ffgo/data/locale/en/LC_MESSAGES/FFGo.mo
ffgo/data/locale/es/LC_MESSAGES/FFGo.mo
ffgo/data/locale/fr/LC_MESSAGES/FFGo.mo
ffgo/data/locale/it/LC_MESSAGES/FFGo.mo
ffgo/data/locale/ja/LC_MESSAGES/FFGo.mo
ffgo/data/locale/nl/LC_MESSAGES/FFGo.mo
ffgo/data/locale/pl/LC_MESSAGES/FFGo.mo
ffgo/data/pics/thumbnail-no-Pillow.gif
ffgo/data/pics/thumbnail-not-avail.png
ffgo/fgdata/__init__.py
ffgo/fgdata/aircraft.py
ffgo/fgdata/airport.py
ffgo/fgdata/apt_dat.py
ffgo/fgdata/fgversion.py
ffgo/fgdata/json_report.py
ffgo/fgdata/parking.py
ffgo/geo/__init__.py
ffgo/geo/geodesy.py
ffgo/geo/magfield.py
ffgo/gui/__init__.py
ffgo/gui/airport_finder.py
ffgo/gui/configwindow.py
ffgo/gui/gps_tool.py
ffgo/gui/infowindow.py
ffgo/gui/mainwindow.py
ffgo/gui/metar.py
ffgo/gui/pressure_converter.py
ffgo/gui/tooltip.py
ffgo/gui/widgets.py
ffgo-1.12.9.dist-info/licenses/COPYING
ffgo-1.12.9.dist-info/licenses/COPYING.Sphinx
ffgo-1.12.9.dist-info/METADATA
ffgo-1.12.9.dist-info/WHEEL
ffgo-1.12.9.dist-info/entry_points.txt
ffgo-1.12.9.dist-info/top_level.txt
ffgo-1.12.9.dist-info/RECORD
