Metadata-Version: 2.4
Name: FFGo
Version: 1.12.9
Summary: A graphical launcher for the FlightGear flight simulator
Author-email: Florent Rougon <f.rougon@frougon.net>
License-Expression: WTFPL
Project-URL: Homepage, https://frougon.net/projects/FFGo/
Project-URL: Screenshots, https://frougon.net/projects/FFGo/gallery/
Project-URL: FFGo doc. on the FlightGear wiki, https://wiki.flightgear.org/FFGo
Project-URL: FFGo conditional config doc., https://frougon.net/projects/FFGo/doc/README-conditional-config/
Project-URL: Repository, https://github.com/frougon/FFGo
Project-URL: Issues, https://github.com/frougon/FFGo/issues
Project-URL: Changelog, https://raw.githubusercontent.com/frougon/FFGo/master/ChangeLog
Keywords: FlightGear,flightgear,flight,simulator,launcher,FFGo,FGo!
Classifier: Development Status :: 5 - Production/Stable
Classifier: Intended Audience :: End Users/Desktop
Classifier: Operating System :: OS Independent
Classifier: Programming Language :: Python :: 3
Classifier: Topic :: Games/Entertainment :: Simulation
Requires-Python: >=3.4
License-File: COPYING
License-File: COPYING.Sphinx
Requires-Dist: CondConfigParser
Provides-Extra: images
Requires-Dist: Pillow; extra == "images"
Provides-Extra: geo
Requires-Dist: geographiclib; extra == "geo"
Dynamic: license-file
